ovos_launcher/__init__.py
ovos_launcher/__main__.py
ovos_launcher/version.py
ovos_launcher-0.1.0a1.dist-info/LICENSE
ovos_launcher-0.1.0a1.dist-info/METADATA
ovos_launcher-0.1.0a1.dist-info/WHEEL
ovos_launcher-0.1.0a1.dist-info/entry_points.txt
ovos_launcher-0.1.0a1.dist-info/top_level.txt
ovos_launcher-0.1.0a1.dist-info/RECORD
